public_admin/__init__.py
public_admin/admin.py
public_admin/exceptions.py
public_admin/sites.py
public_admin/templates/admin/base.html
public_admin/templates/admin/index.html
django_public_admin-0.0.6.dist-info/LICENSE
django_public_admin-0.0.6.dist-info/METADATA
django_public_admin-0.0.6.dist-info/WHEEL
django_public_admin-0.0.6.dist-info/RECORD
