Metadata-Version: 2.1
Name: django-public-admin
Version: 0.0.6
Summary: A public read-only version of the Django Admin
Home-page: https://github.com/cuducos/django-public-admin
License: MIT
Author: Eduardo Cuducos
Author-email: cuducos@users.noreply.github.com
Requires-Python: >=3.9,<4.0
Classifier: Development Status :: 3 - Alpha
Classifier: Framework :: Django
Classifier: Framework :: Django :: 3.2
Classifier: Framework :: Django :: 4.2
Classifier: Framework :: Django :: 5.0
Classifier: Intended Audience :: Developers
Classifier: License :: OSI Approved :: MIT License
Classifier: Programming Language :: Python :: 3
Classifier: Programming Language :: Python :: 3.9
Classifier: Programming Language :: Python :: 3.10
Classifier: Programming Language :: Python :: 3.11
Classifier: Programming Language :: Python :: 3.12
Classifier: Topic :: Software Development
Requires-Dist: django (>=3.2)
Project-URL: Repository, https://github.com/cuducos/django-public-admin
